wetrocloud/__init__.py
wetrocloud/api_client.py
wetrocloud/client.py
wetrocloud/collection.py
wetrocloud/custom_response.py
wetrocloud/custom_types.py
wetrocloud/rag.py
wetrocloud/toolkit.py
wetrocloud-0.1.5.dist-info/LICENSE
wetrocloud-0.1.5.dist-info/METADATA
wetrocloud-0.1.5.dist-info/WHEEL
wetrocloud-0.1.5.dist-info/top_level.txt
wetrocloud-0.1.5.dist-info/RECORD
