Metadata-Version: 2.2
Name: wetrocloud
Version: 0.1.5
Summary: Wetrocloud's Official SDK
Home-page: https://docs.wetrocloud.com/
Author: Wetrocloud Inc
Author-email: bolu@wetrocloud.com
Classifier: Programming Language :: Python :: 3
Classifier: License :: OSI Approved :: MIT License
Classifier: Operating System :: OS Independent
Requires-Python: >=3.6
License-File: LICENSE
Requires-Dist: requests
Requires-Dist: pydantic
Requires-Dist: typing_extensions
Dynamic: author
Dynamic: author-email
Dynamic: classifier
Dynamic: description
Dynamic: description-content-type
Dynamic: home-page
Dynamic: requires-dist
Dynamic: requires-python
Dynamic: summary
